depsolve/__init__.py
depsolve/depsolve.py
depsolve/exceptions.py
depsolve/models.py
depsolve-0.2.1.dist-info/METADATA
depsolve-0.2.1.dist-info/WHEEL
depsolve-0.2.1.dist-info/RECORD
