Metadata-Version: 2.1
Name: depsolve
Version: 0.2.1
Summary: Agnostic dependencies solver
License: MIT
Author: Sebastien Nicolet
Author-email: snicolet95@gmail.com
Requires-Python: >=3.10,<4.0
Classifier: License :: OSI Approved :: MIT License
Classifier: Programming Language :: Python :: 3
Classifier: Programming Language :: Python :: 3.10
Classifier: Programming Language :: Python :: 3.11
Requires-Dist: pydantic (>=2.4.2,<3.0.0)
